namaztime/__init__.py
namaztime/timezone_city.json
namaztime/waqt.py
namaztime-1.1.0.dist-info/licenses/LICENSE
tests/__init__.py
tests/test_namaztime.py
namaztime-1.1.0.dist-info/METADATA
namaztime-1.1.0.dist-info/WHEEL
namaztime-1.1.0.dist-info/top_level.txt
namaztime-1.1.0.dist-info/RECORD
