Metadata-Version: 2.4
Name: namaztime
Version: 1.1.0
Summary: Python package to get Islamic prayer times for any city using Aladhan API, for Muslims and Islam
Home-page: https://github.com/raxmatulloxswe/NamazTime-API
Author: raxmatullox
Author-email: raxmatulllox@icloud.com
Classifier: Programming Language :: Python :: 3
Classifier: License :: OSI Approved :: MIT License
Classifier: Operating System :: OS Independent
Requires-Python: >=3.6
License-File: LICENSE
Requires-Dist: requests>=2.25.1
Dynamic: author
Dynamic: author-email
Dynamic: classifier
Dynamic: description
Dynamic: description-content-type
Dynamic: home-page
Dynamic: license-file
Dynamic: requires-dist
Dynamic: requires-python
Dynamic: summary
